[
    {
        "image": "./images/readme-write.png",
        "alt": "first project card",
        "heading": "readme-write",
        "summary": "Use the bash command line to write a project readme.",
        "description": "Employs Inquirer and a modicum of modularity to write the best readmes yet seen.",
        "repo": "https://github.com/S-R-i-c-e/readme-write"
    },
    {
        "image": "./images/travellers-friend.png",
        "alt": "second project card",
        "heading": "The Traveller's Friend",
        "summary": "Group project using various API's to assist the traveller",
        "description": "Employs Bootstrap, three server-side API's, and local storage.",
        "repo": "https://github.com/S-R-i-c-e/TheAntonLeeSteveProject"
    },
    {
        "image": "./assets/images/feigenbaum.png",
        "alt": "first project card",
        "heading": "readme-write",
        "summary": "Use the bash command line to write a project readme.",
        "description": "Employs Inquirer and a modicum of modularity to write the best readmes yet seen.",
        "repo": "https://github.com/S-R-i-c-e/feigenbaum"
    },
    {
        "image": "./assets/images/readme-write.png",
        "alt": "first project card",
        "heading": "readme-write",
        "summary": "Use the bash command line to write a project readme.",
        "description": "Employs Inquirer and a modicum of modularity to write the best readmes yet seen.",
        "repo": "https://github.com/S-R-i-c-e/readme-write"
    },
    {
        "image": "./assets/images/readme-write.png",
        "alt": "first project card",
        "heading": "readme-write",
        "summary": "Use the bash command line to write a project readme.",
        "description": "Employs Inquirer and a modicum of modularity to write the best readmes yet seen.",
        "repo": "https://github.com/S-R-i-c-e/readme-write"
    },
    {
        "image": "./assets/images/readme-write.png",
        "alt": "first project card",
        "heading": "readme-write",
        "summary": "Use the bash command line to write a project readme.",
        "description": "Employs Inquirer and a modicum of modularity to write the best readmes yet seen.",
        "repo": "https://github.com/S-R-i-c-e/readme-write"
    }
]